futurevision/SSD_MobileNet.caffemodel
futurevision/SSD_MobileNet_prototxt.txt
futurevision/__init__.py
futurevision/arduino.py
futurevision/dlib_face_recognition_resnet_model_v1.dat
futurevision/iphone.py
futurevision/raspberrypi.py
futurevision/vision.py
futurevision-0.1.5.dist-info/LICENSE
futurevision-0.1.5.dist-info/METADATA
futurevision-0.1.5.dist-info/WHEEL
futurevision-0.1.5.dist-info/top_level.txt
futurevision-0.1.5.dist-info/RECORD
